{
  "version": "1",
  "cognitoConfig": {
    "identityPoolName": "dish5aed8c8f_identitypool_5aed8c8f",
    "allowUnauthenticatedIdentities": false,
    "resourceNameTruncated": "dish5aed8c8f",
    "userPoolName": "dish5aed8c8f_userpool_5aed8c8f",
    "autoVerifiedAttributes": [
      "email"
    ],
    "mfaConfiguration": "OFF",
    "mfaTypes": [
      "SMS Text Message"
    ],
    "smsAuthenticationMessage": "Your authentication code is {####}",
    "smsVerificationMessage": "Your verification code is {####}",
    "emailVerificationSubject": "Your verification code",
    "emailVerificationMessage": "Your verification code is {####}",
    "defaultPasswordPolicy": false,
    "passwordPolicyMinLength": 8,
    "passwordPolicyCharacters": [],
    "requiredAttributes": [
      "email"
    ],
    "aliasAttributes": [],
    "userpoolClientGenerateSecret": false,
    "userpoolClientRefreshTokenValidity": 30,
    "userpoolClientWriteAttributes": [
      "email"
    ],
    "userpoolClientReadAttributes": [
      "email"
    ],
    "userpoolClientLambdaRole": "dish5a5aed8c8f_userpoolclient_lambda_role",
    "userpoolClientSetAttributes": false,
    "sharedId": "5aed8c8f",
    "resourceName": "dish5aed8c8f",
    "authSelections": "identityPoolAndUserPool",
    "useDefault": "default",
    "usernameAttributes": [
      "email"
    ],
    "triggers": {},
    "userPoolGroupList": [],
    "serviceName": "Cognito",
    "usernameCaseSensitive": false,
    "useEnabledMfas": true
  }
}